bitstruct_annotated/__init__.py
bitstruct_annotated/py.typed
bitstruct_annotated-0.1.4.dist-info/licenses/LICENSE
bitstruct_annotated-0.1.4.dist-info/METADATA
bitstruct_annotated-0.1.4.dist-info/WHEEL
bitstruct_annotated-0.1.4.dist-info/top_level.txt
bitstruct_annotated-0.1.4.dist-info/RECORD
