Metadata-Version: 2.4
Name: bitstruct-annotated
Version: 0.1.4
Summary: Annotate fields with bitstruct un/packing instructions
Author-email: Oliver Kleinke <oliver.kleinke@c-01a.de>
Project-URL: Source, https://github.com/okleinke/bitstruct-annotated/
Keywords: bitstruct,struct,annotated,packing,serialization
Classifier: Development Status :: 3 - Alpha
Classifier: License :: OSI Approved :: GNU Affero General Public License v3 or later (AGPLv3+)
Classifier: Natural Language :: English
Classifier: Programming Language :: Python :: 3.11
Classifier: Programming Language :: Python :: 3.12
Classifier: Programming Language :: Python :: 3.13
Classifier: Topic :: Software Development :: Libraries :: Python Modules
Classifier: Intended Audience :: Developers
Requires-Python: >=3.11
License-File: LICENSE
Requires-Dist: bitstruct
Provides-Extra: dev
Requires-Dist: build; extra == "dev"
Requires-Dist: mypy; extra == "dev"
Requires-Dist: pydantic; extra == "dev"
Requires-Dist: pyproject-scripts; extra == "dev"
Requires-Dist: pytest; extra == "dev"
Requires-Dist: pytest-cov; extra == "dev"
Requires-Dist: ruff; extra == "dev"
Dynamic: license-file
